odoo/addons/hr_timesheet_predefined_description_rules/README.rst
odoo/addons/hr_timesheet_predefined_description_rules/__init__.py
odoo/addons/hr_timesheet_predefined_description_rules/__manifest__.py
odoo/addons/hr_timesheet_predefined_description_rules/i18n/es.po
odoo/addons/hr_timesheet_predefined_description_rules/i18n/hr_timesheet_predefined_description_rules.pot
odoo/addons/hr_timesheet_predefined_description_rules/i18n/it.po
odoo/addons/hr_timesheet_predefined_description_rules/models/__init__.py
odoo/addons/hr_timesheet_predefined_description_rules/models/account_analytic_line.py
odoo/addons/hr_timesheet_predefined_description_rules/models/hr_timesheet_predefined_description.py
odoo/addons/hr_timesheet_predefined_description_rules/readme/CONFIGURE.rst
odoo/addons/hr_timesheet_predefined_description_rules/readme/CONTRIBUTORS.rst
odoo/addons/hr_timesheet_predefined_description_rules/readme/DESCRIPTION.rst
odoo/addons/hr_timesheet_predefined_description_rules/readme/USAGE.rst
odoo/addons/hr_timesheet_predefined_description_rules/static/description/icon.png
odoo/addons/hr_timesheet_predefined_description_rules/static/description/index.html
odoo/addons/hr_timesheet_predefined_description_rules/tests/__init__.py
odoo/addons/hr_timesheet_predefined_description_rules/tests/test_account_analytic_line.py
odoo/addons/hr_timesheet_predefined_description_rules/tests/test_hr_timesheet_predefined_description.py
odoo/addons/hr_timesheet_predefined_description_rules/views/account_analytic_line_views.xml
odoo/addons/hr_timesheet_predefined_description_rules/views/timesheet_predefined_description_views.xml
odoo_addon_hr_timesheet_predefined_description_rules-16.0.1.0.0.3.dist-info/METADATA
odoo_addon_hr_timesheet_predefined_description_rules-16.0.1.0.0.3.dist-info/WHEEL
odoo_addon_hr_timesheet_predefined_description_rules-16.0.1.0.0.3.dist-info/top_level.txt
odoo_addon_hr_timesheet_predefined_description_rules-16.0.1.0.0.3.dist-info/RECORD
