Metadata-Version: 2.1
Name: odoo-addon-hr_timesheet_predefined_description_rules
Version: 16.0.1.0.0.3
Summary: Manage predefined descriptions for timesheet entries
Home-page: https://github.com/OCA/timesheet
Author: Sygel, Odoo Community Association (OCA)
Author-email: support@odoo-community.org
License: AGPL-3
Classifier: Programming Language :: Python
Classifier: Framework :: Odoo
Classifier: Framework :: Odoo :: 16.0
Classifier: License :: OSI Approved :: GNU Affero General Public License v3
Requires-Python: >=3.10
Requires-Dist: odoo-addon-hr-timesheet-predefined-description<16.1dev,>=16.0dev
Requires-Dist: odoo-addon-hr-timesheet-sheet<16.1dev,>=16.0dev
Requires-Dist: odoo<16.1dev,>=16.0a
